torchlearn/__init__.py
torchlearn/metric/__init__.py
torchlearn/metric/average_metric.py
torchlearn/metric/classification.py
torchlearn/metric/loss.py
torchlearn/metric/metric.py
torchlearn/metric/metric_dict.py
torchlearn/metric/metric_value.py
torchlearn/metric/state.py
torchlearn/model/__init__.py
torchlearn/model/classifier.py
torchlearn/model/mlp.py
torchlearn/model/perceptron.py
torchlearn/objective/__init__.py
torchlearn/objective/objective.py
torchlearn/objective/pareto.py
torchlearn/processing/__init__.py
torchlearn/processing/graph.py
torchlearn/training/__init__.py
torchlearn/training/callback.py
torchlearn/training/early_stopping.py
torchlearn/training/pareto.py
torchlearn/training/results.py
torchlearn/training/schedulers.py
torchlearn/training/trainer.py
torchlearn/utils/__init__.py
torchlearn/utils/arguments.py
torchlearn/utils/graph.py
torchlearn/utils/numbers.py
torchlearn-0.2.2.dist-info/LICENSE
torchlearn-0.2.2.dist-info/METADATA
torchlearn-0.2.2.dist-info/WHEEL
torchlearn-0.2.2.dist-info/top_level.txt
torchlearn-0.2.2.dist-info/RECORD
